{
  "$schema": "https://mintlify.com/docs.json",
  "theme": "willow",
  "name": "Flexdoc APIs",
  "colors": {
    "primary": "#2c7bbf",
    "light": "#4188c5",
    "dark": "#276ca8"
  },
  "seo": {
    "metatags": {
      "robots": "noindex"
    }
  },
  "favicon": "/favicon.png",
  "navigation": {
    "tabs": [
      {
        "tab": "Documentação",
        "groups": [
          {
            "group": "Comece aqui",
            "icon": "rocket",
            "pages": [
              "index"
            ]
          },
          {
            "group": "Soluções",
            "icon": "lightbulb-on",
            "pages": [
              "documentation/onboarding",
              "documentation/backgroundcheck"
            ]
          }
        ]
      },
      {
        "tab": "Referência da API",
        "anchors": [
          {
            "anchor": "Comece aqui",
            "icon": "rocket",
            "pages": [
              "api-pages/v1-intro",
              "api-pages/bpo-intro"
            ]
          },
          {
            "anchor": "APIs",
            "icon": "square-terminal",
            "groups":[
              {
                "group": "V1",
                "openapi": "https://flex-hml.flexdoc-apis.com.br/services/docs/0-services"
              },
              {
                "group": "BPO",
                "openapi": "https://flex-des.flexdoc-apis.com.br/import/v3/api-docs/Documenta%C3%A7%C3%A3o%20Completa"
              }
            ]
          },
          {
            "anchor": "Enums",
            "icon": "table-list",
            "pages": [
              "api-pages/onboarding-status",
              "api-pages/process-type"
            ]
          }
        ]
      }
    ]
  },
  "logo": {
    "light": "/logo/flexdoc-logo-light.png",
    "dark": "/logo/flexdoc-logo-dark.png"
  },
  "navbar": {
    "primary": {
      "type": "button",
      "label": "Dashboard",
      "href": "https://dashboard.flexdoc-apis.com.br/"
    }
  },
  "footer": {
    "socials": {}
  }
}
